karrio/mappers/dpd_meta/__init__.py
karrio/mappers/dpd_meta/mapper.py
karrio/mappers/dpd_meta/proxy.py
karrio/mappers/dpd_meta/settings.py
karrio/plugins/dpd_meta/__init__.py
karrio/providers/dpd_meta/__init__.py
karrio/providers/dpd_meta/error.py
karrio/providers/dpd_meta/units.py
karrio/providers/dpd_meta/utils.py
karrio/providers/dpd_meta/pickup/__init__.py
karrio/providers/dpd_meta/pickup/create.py
karrio/providers/dpd_meta/shipment/__init__.py
karrio/providers/dpd_meta/shipment/create.py
karrio/schemas/dpd_meta/__init__.py
karrio/schemas/dpd_meta/error_response.py
karrio/schemas/dpd_meta/pickup_create_request.py
karrio/schemas/dpd_meta/pickup_create_response.py
karrio/schemas/dpd_meta/shipment_request.py
karrio/schemas/dpd_meta/shipment_response.py
karrio_dpd_meta-2026.1.4.dist-info/METADATA
karrio_dpd_meta-2026.1.4.dist-info/WHEEL
karrio_dpd_meta-2026.1.4.dist-info/entry_points.txt
karrio_dpd_meta-2026.1.4.dist-info/top_level.txt
karrio_dpd_meta-2026.1.4.dist-info/RECORD
